mlclassifier/__init__.py
mlclassifier/ml.py
mlclassifier/trainer.py
mlclassifier/version.py
mlclassifier-1.1.0.dist-info/METADATA
mlclassifier-1.1.0.dist-info/WHEEL
mlclassifier-1.1.0.dist-info/top_level.txt
mlclassifier-1.1.0.dist-info/RECORD
